yaqd_seek/VERSION
yaqd_seek/__init__.py
yaqd_seek/__version__.py
yaqd_seek/_seek_compact.py
yaqd_seek/_seek_compact_client_feed.py
yaqd_seek/seek-compact.avpr
yaqd_seek/seek-compact.toml
yaqd_seek-2022.11.0.dist-info/entry_points.txt
yaqd_seek-2022.11.0.dist-info/LICENSE
yaqd_seek-2022.11.0.dist-info/WHEEL
yaqd_seek-2022.11.0.dist-info/METADATA
yaqd_seek-2022.11.0.dist-info/RECORD
