Metadata-Version: 2.1
Name: yaqd-seek
Version: 2022.11.0
Summary: yaq daemons for Seek thermal cameras
Home-page: https://yaq.fyi
Author: Dan Kohler
Requires-Python: >=3.7
Classifier: Development Status :: 2 - Pre-Alpha
Classifier: Intended Audience :: Science/Research
Classifier: License :: OSI Approved :: GNU Lesser General Public License v3 (LGPLv3)
Classifier: Natural Language :: English
Classifier: Programming Language :: Python :: 3
Classifier: Programming Language :: Python :: 3.7
Classifier: Programming Language :: Python :: 3.8
Classifier: Topic :: Scientific/Engineering
Requires-Dist: yaqd-core>=2022.5.0
Requires-Dist: pyusb
Requires-Dist: numpy
Requires-Dist: black ; extra == "dev"
Requires-Dist: pre-commit ; extra == "dev"
Project-URL: Issues, https://github.com/yaq-project/yaqd-seek/issues
Project-URL: Source, https://github.com/yaq-project/yaqd-seek
Provides-Extra: dev
